[
  {
    "inputs": [],
    "name": "getTotalRoyaltyShares",
    "outputs": [
      {
        "internalType": "uint256",
        "name": "",
        "type": "uint256"
      }
    ],
    "stateMutability": "view",
    "type": "function"
  },
  {
    "inputs": [],
    "name": "getTotalShares",
    "outputs": [
      {
        "internalType": "uint256",
        "name": "",
        "type": "uint256"
      }
    ],
    "stateMutability": "view",
    "type": "function"
  },
  {
    "inputs": [
      {
        "internalType": "address",
        "name": "account",
        "type": "address"
      }
    ],
    "name": "release",
    "outputs": [],
    "stateMutability": "nonpayable",
    "type": "function"
  },
  {
    "inputs": [],
    "name": "splitPayment",
    "outputs": [],
    "stateMutability": "payable",
    "type": "function"
  },
  {
    "inputs": [
      {
        "internalType": "uint8",
        "name": "paymentType",
        "type": "uint8"
      },
      {
        "internalType": "uint256",
        "name": "payeeIndex",
        "type": "uint256"
      },
      {
        "internalType": "address",
        "name": "newPayee",
        "type": "address"
      }
    ],
    "name": "updatePayee",
    "outputs": [],
    "stateMutability": "nonpayable",
    "type": "function"
  }
]